[
  {
    "title": "Odyssey 1",
    "length": "04:40",
    "link": "https://archive.org/download/Odyssey201612/Odyssey%201.mp3"
  }, {
    "title": "Odyssey 2",
    "length": "02:32",
    "link": "https://archive.org/download/Odyssey201612/Odyssey%202.mp3"
  }, {
    "title": "Odyssey 3",
    "length": "03:19",
    "link": "https://archive.org/download/Odyssey201612/Odyssey%203.mp3"
  }, {
    "title": "Odyssey 4",
    "length": "04:13",
    "link": "https://archive.org/download/Odyssey201612/Odyssey%204.mp3"
  }, {
    "title": "Odyssey 5",
    "length": "03:44",
    "link": "https://archive.org/download/Odyssey201612/Odyssey%205.mp3"
  }, {
    "title": "Odyssey 6",
    "length": "04:51",
    "link": "https://archive.org/download/Odyssey201612/Odyssey%206.mp3"
  }
]
